GRO/__init__.py
GRO/classGRO.py
GRO/gro.py
copernic/__init__.py
copernic/classDTCO.py
copernic/classVSDataset.py
libMetric/__init__.py
libMetric/classLiberty.py
DTCO-0.1.4.dist-info/LICENSE
DTCO-0.1.4.dist-info/METADATA
DTCO-0.1.4.dist-info/WHEEL
DTCO-0.1.4.dist-info/top_level.txt
DTCO-0.1.4.dist-info/RECORD
