Metadata-Version: 2.1
Name: DTCO
Version: 0.1.4
Summary: DTCO Utility
Home-page: https://github.com/dipsci/DTCO
Author: hockchen
Author-email: hock.chen@dipsci.com
Keywords: DTCO,process monitor,liberty,metric,timing,EDA,physical design,WAT,CP,Binning,Virtual Silicon
Classifier: Programming Language :: Python :: 3
Classifier: License :: OSI Approved :: MIT License
License-File: LICENSE
